[
    {
        "stmtType": "Class",
        "name": "XMLReader",
        "fqn": "\\XMLReader",
        "type": 0,
        "extendsClass": "",
        "methods": [
            {
                "name": "close",
                "type": 1,
                "byRef": false,
                "params": [

                ],
                "doc": "\/**\n * (PHP 5 &gt;= 5.1.0)<br\/>\n * Close the XMLReader input\n * @link http:\/\/php.net\/manual\/en\/xmlreader.close.php\n * @return bool <b>TRUE<\/b> on success or <b>FALSE<\/b> on failure.\n *\/"
            },
            {
                "name": "getAttribute",
                "type": 1,
                "byRef": false,
                "params": [
                    {
                        "name": "name",
                        "type": null,
                        "byRef": false,
                        "default": ""
                    }
                ],
                "doc": "\/**\n * (PHP 5 &gt;= 5.1.0)<br\/>\n * Get the value of a named attribute\n * @link http:\/\/php.net\/manual\/en\/xmlreader.getattribute.php\n * @param string $name <p>\n * The name of the attribute.\n * <\/p>\n * @return string The value of the attribute, or <b>NULL<\/b> if no attribute with the given\n * <i>name<\/i> is found or not positioned on an element node.\n *\/"
            },
            {
                "name": "getAttributeNo",
                "type": 1,
                "byRef": false,
                "params": [
                    {
                        "name": "index",
                        "type": null,
                        "byRef": false,
                        "default": ""
                    }
                ],
                "doc": "\/**\n * (PHP 5 &gt;= 5.1.0)<br\/>\n * Get the value of an attribute by index\n * @link http:\/\/php.net\/manual\/en\/xmlreader.getattributeno.php\n * @param int $index <p>\n * The position of the attribute.\n * <\/p>\n * @return string The value of the attribute, or an empty string if no attribute exists\n * at <i>index<\/i> or not positioned of element.\n *\/"
            },
            {
                "name": "getAttributeNs",
                "type": 1,
                "byRef": false,
                "params": [
                    {
                        "name": "localName",
                        "type": null,
                        "byRef": false,
                        "default": ""
                    },
                    {
                        "name": "namespaceURI",
                        "type": null,
                        "byRef": false,
                        "default": ""
                    }
                ],
                "doc": "\/**\n * (PHP 5 &gt;= 5.1.0)<br\/>\n * Get the value of an attribute by localname and URI\n * @link http:\/\/php.net\/manual\/en\/xmlreader.getattributens.php\n * @param string $localName <p>\n * The local name.\n * <\/p>\n * @param string $namespaceURI <p>\n * The namespace URI.\n * <\/p>\n * @return string The value of the attribute, or an empty string if no attribute with the\n * given <i>localName<\/i> and\n * <i>namespaceURI<\/i> is found or not positioned of element.\n *\/"
            },
            {
                "name": "getParserProperty",
                "type": 1,
                "byRef": false,
                "params": [
                    {
                        "name": "property",
                        "type": null,
                        "byRef": false,
                        "default": ""
                    }
                ],
                "doc": "\/**\n * (PHP 5 &gt;= 5.1.0)<br\/>\n * Indicates if specified property has been set\n * @link http:\/\/php.net\/manual\/en\/xmlreader.getparserproperty.php\n * @param int $property <p>\n * One of the parser option\n * constants.\n * <\/p>\n * @return bool <b>TRUE<\/b> on success or <b>FALSE<\/b> on failure.\n *\/"
            },
            {
                "name": "isValid",
                "type": 1,
                "byRef": false,
                "params": [

                ],
                "doc": "\/**\n * (PHP 5 &gt;= 5.1.0)<br\/>\n * Indicates if the parsed document is valid\n * @link http:\/\/php.net\/manual\/en\/xmlreader.isvalid.php\n * @return bool <b>TRUE<\/b> on success or <b>FALSE<\/b> on failure.\n *\/"
            },
            {
                "name": "lookupNamespace",
                "type": 1,
                "byRef": false,
                "params": [
                    {
                        "name": "prefix",
                        "type": null,
                        "byRef": false,
                        "default": ""
                    }
                ],
                "doc": "\/**\n * (PHP 5 &gt;= 5.1.0)<br\/>\n * Lookup namespace for a prefix\n * @link http:\/\/php.net\/manual\/en\/xmlreader.lookupnamespace.php\n * @param string $prefix <p>\n * String containing the prefix.\n * <\/p>\n * @return bool <b>TRUE<\/b> on success or <b>FALSE<\/b> on failure.\n *\/"
            },
            {
                "name": "moveToAttributeNo",
                "type": 1,
                "byRef": false,
                "params": [
                    {
                        "name": "index",
                        "type": null,
                        "byRef": false,
                        "default": ""
                    }
                ],
                "doc": "\/**\n * (PHP 5 &gt;= 5.1.0)<br\/>\n * Move cursor to an attribute by index\n * @link http:\/\/php.net\/manual\/en\/xmlreader.movetoattributeno.php\n * @param int $index <p>\n * The position of the attribute.\n * <\/p>\n * @return bool <b>TRUE<\/b> on success or <b>FALSE<\/b> on failure.\n *\/"
            },
            {
                "name": "moveToAttribute",
                "type": 1,
                "byRef": false,
                "params": [
                    {
                        "name": "name",
                        "type": null,
                        "byRef": false,
                        "default": ""
                    }
                ],
                "doc": "\/**\n * (PHP 5 &gt;= 5.1.0)<br\/>\n * Move cursor to a named attribute\n * @link http:\/\/php.net\/manual\/en\/xmlreader.movetoattribute.php\n * @param string $name <p>\n * The name of the attribute.\n * <\/p>\n * @return bool <b>TRUE<\/b> on success or <b>FALSE<\/b> on failure.\n *\/"
            },
            {
                "name": "moveToAttributeNs",
                "type": 1,
                "byRef": false,
                "params": [
                    {
                        "name": "localName",
                        "type": null,
                        "byRef": false,
                        "default": ""
                    },
                    {
                        "name": "namespaceURI",
                        "type": null,
                        "byRef": false,
                        "default": ""
                    }
                ],
                "doc": "\/**\n * (PHP 5 &gt;= 5.1.0)<br\/>\n * Move cursor to a named attribute\n * @link http:\/\/php.net\/manual\/en\/xmlreader.movetoattributens.php\n * @param string $localName <p>\n * The local name.\n * <\/p>\n * @param string $namespaceURI <p>\n * The namespace URI.\n * <\/p>\n * @return bool <b>TRUE<\/b> on success or <b>FALSE<\/b> on failure.\n *\/"
            },
            {
                "name": "moveToElement",
                "type": 1,
                "byRef": false,
                "params": [

                ],
                "doc": "\/**\n * (PHP 5 &gt;= 5.1.0)<br\/>\n * Position cursor on the parent Element of current Attribute\n * @link http:\/\/php.net\/manual\/en\/xmlreader.movetoelement.php\n * @return bool <b>TRUE<\/b> if successful and <b>FALSE<\/b> if it fails or not positioned on\n * Attribute when this method is called.\n *\/"
            },
            {
                "name": "moveToFirstAttribute",
                "type": 1,
                "byRef": false,
                "params": [

                ],
                "doc": "\/**\n * (PHP 5 &gt;= 5.1.0)<br\/>\n * Position cursor on the first Attribute\n * @link http:\/\/php.net\/manual\/en\/xmlreader.movetofirstattribute.php\n * @return bool <b>TRUE<\/b> on success or <b>FALSE<\/b> on failure.\n *\/"
            },
            {
                "name": "moveToNextAttribute",
                "type": 1,
                "byRef": false,
                "params": [

                ],
                "doc": "\/**\n * (PHP 5 &gt;= 5.1.0)<br\/>\n * Position cursor on the next Attribute\n * @link http:\/\/php.net\/manual\/en\/xmlreader.movetonextattribute.php\n * @return bool <b>TRUE<\/b> on success or <b>FALSE<\/b> on failure.\n *\/"
            },
            {
                "name": "open",
                "type": 1,
                "byRef": false,
                "params": [
                    {
                        "name": "URI",
                        "type": null,
                        "byRef": false,
                        "default": ""
                    },
                    {
                        "name": "encoding",
                        "type": null,
                        "byRef": false,
                        "default": null
                    },
                    {
                        "name": "options",
                        "type": null,
                        "byRef": false,
                        "default": 0
                    }
                ],
                "doc": "\/**\n * (PHP 5 &gt;= 5.1.0)<br\/>\n * Set the URI containing the XML to parse\n * @link http:\/\/php.net\/manual\/en\/xmlreader.open.php\n * @param string $URI <p>\n * URI pointing to the document.\n * <\/p>\n * @param string $encoding [optional] <p>\n * The document encoding or <b>NULL<\/b>.\n * <\/p>\n * @param int $options [optional] <p>\n * A bitmask of the LIBXML_*\n * constants.\n * <\/p>\n * @return bool <b>TRUE<\/b> on success or <b>FALSE<\/b> on failure. If called statically, returns an\n * <b>XMLReader<\/b> or <b>FALSE<\/b> on failure.\n *\/"
            },
            {
                "name": "read",
                "type": 1,
                "byRef": false,
                "params": [

                ],
                "doc": "\/**\n * (PHP 5 &gt;= 5.1.0)<br\/>\n * Move to next node in document\n * @link http:\/\/php.net\/manual\/en\/xmlreader.read.php\n * @return bool <b>TRUE<\/b> on success or <b>FALSE<\/b> on failure.\n *\/"
            },
            {
                "name": "next",
                "type": 1,
                "byRef": false,
                "params": [
                    {
                        "name": "localname",
                        "type": null,
                        "byRef": false,
                        "default": null
                    }
                ],
                "doc": "\/**\n * (PHP 5 &gt;= 5.1.0)<br\/>\n * Move cursor to next node skipping all subtrees\n * @link http:\/\/php.net\/manual\/en\/xmlreader.next.php\n * @param string $localname [optional] <p>\n * The name of the next node to move to.\n * <\/p>\n * @return bool <b>TRUE<\/b> on success or <b>FALSE<\/b> on failure.\n *\/"
            },
            {
                "name": "readInnerXml",
                "type": 1,
                "byRef": false,
                "params": [

                ],
                "doc": "\/**\n * (PHP 5 &gt;= 5.2.0)<br\/>\n * Retrieve XML from current node\n * @link http:\/\/php.net\/manual\/en\/xmlreader.readinnerxml.php\n * @return string the contents of the current node as a string. Empty string on failure.\n *\/"
            },
            {
                "name": "readOuterXml",
                "type": 1,
                "byRef": false,
                "params": [

                ],
                "doc": "\/**\n * (PHP 5 &gt;= 5.2.0)<br\/>\n * Retrieve XML from current node, including it self\n * @link http:\/\/php.net\/manual\/en\/xmlreader.readouterxml.php\n * @return string the contents of current node, including itself, as a string. Empty string on failure.\n *\/"
            },
            {
                "name": "readString",
                "type": 1,
                "byRef": false,
                "params": [

                ],
                "doc": "\/**\n * (PHP 5 &gt;= 5.2.0)<br\/>\n * Reads the contents of the current node as a string\n * @link http:\/\/php.net\/manual\/en\/xmlreader.readstring.php\n * @return string the content of the current node as a string. Empty string on\n * failure.\n *\/"
            },
            {
                "name": "setSchema",
                "type": 1,
                "byRef": false,
                "params": [
                    {
                        "name": "filename",
                        "type": null,
                        "byRef": false,
                        "default": ""
                    }
                ],
                "doc": "\/**\n * (PHP 5 &gt;= 5.2.0)<br\/>\n * Validate document against XSD\n * @link http:\/\/php.net\/manual\/en\/xmlreader.setschema.php\n * @param string $filename <p>\n * The filename of the XSD schema.\n * <\/p>\n * @return bool <b>TRUE<\/b> on success or <b>FALSE<\/b> on failure.\n *\/"
            },
            {
                "name": "setParserProperty",
                "type": 1,
                "byRef": false,
                "params": [
                    {
                        "name": "property",
                        "type": null,
                        "byRef": false,
                        "default": ""
                    },
                    {
                        "name": "value",
                        "type": null,
                        "byRef": false,
                        "default": ""
                    }
                ],
                "doc": "\/**\n * (PHP 5 &gt;= 5.1.0)<br\/>\n * Set parser options\n * @link http:\/\/php.net\/manual\/en\/xmlreader.setparserproperty.php\n * @param int $property <p>\n * One of the parser option\n * constants.\n * <\/p>\n * @param bool $value <p>\n * If set to <b>TRUE<\/b> the option will be enabled otherwise will\n * be disabled.\n * <\/p>\n * @return bool <b>TRUE<\/b> on success or <b>FALSE<\/b> on failure.\n *\/"
            },
            {
                "name": "setRelaxNGSchema",
                "type": 1,
                "byRef": false,
                "params": [
                    {
                        "name": "filename",
                        "type": null,
                        "byRef": false,
                        "default": ""
                    }
                ],
                "doc": "\/**\n * (PHP 5 &gt;= 5.2.0)<br\/>\n * Set the filename or URI for a RelaxNG Schema\n * @link http:\/\/php.net\/manual\/en\/xmlreader.setrelaxngschema.php\n * @param string $filename <p>\n * filename or URI pointing to a RelaxNG Schema.\n * <\/p>\n * @return bool <b>TRUE<\/b> on success or <b>FALSE<\/b> on failure.\n *\/"
            },
            {
                "name": "setRelaxNGSchemaSource",
                "type": 1,
                "byRef": false,
                "params": [
                    {
                        "name": "source",
                        "type": null,
                        "byRef": false,
                        "default": ""
                    }
                ],
                "doc": "\/**\n * (PHP 5 &gt;= 5.1.0)<br\/>\n * Set the data containing a RelaxNG Schema\n * @link http:\/\/php.net\/manual\/en\/xmlreader.setrelaxngschemasource.php\n * @param string $source <p>\n * String containing the RelaxNG Schema.\n * <\/p>\n * @return bool <b>TRUE<\/b> on success or <b>FALSE<\/b> on failure.\n *\/"
            },
            {
                "name": "XML",
                "type": 1,
                "byRef": false,
                "params": [
                    {
                        "name": "source",
                        "type": null,
                        "byRef": false,
                        "default": ""
                    },
                    {
                        "name": "encoding",
                        "type": null,
                        "byRef": false,
                        "default": null
                    },
                    {
                        "name": "options",
                        "type": null,
                        "byRef": false,
                        "default": 0
                    }
                ],
                "doc": "\/**\n * (PHP 5 &gt;= 5.1.0)<br\/>\n * Set the data containing the XML to parse\n * @link http:\/\/php.net\/manual\/en\/xmlreader.xml.php\n * @param string $source <p>\n * String containing the XML to be parsed.\n * <\/p>\n * @param string $encoding [optional] <p>\n * The document encoding or <b>NULL<\/b>.\n * <\/p>\n * @param int $options [optional] <p>\n * A bitmask of the LIBXML_*\n * constants.\n * <\/p>\n * @return bool <b>TRUE<\/b> on success or <b>FALSE<\/b> on failure. If called statically, returns an\n * <b>XMLReader<\/b> or <b>FALSE<\/b> on failure.\n *\/"
            },
            {
                "name": "expand",
                "type": 1,
                "byRef": false,
                "params": [
                    {
                        "name": "basenode",
                        "type": "DOMNode",
                        "byRef": false,
                        "default": null
                    }
                ],
                "doc": "\/**\n * (PHP 5 &gt;= 5.1.0)<br\/>\n * Returns a copy of the current node as a DOM object\n * @link http:\/\/php.net\/manual\/en\/xmlreader.expand.php\n * @param DOMNode $basenode [optional]\n * @return DOMNode The resulting <b>DOMNode<\/b> or <b>FALSE<\/b> on error.\n *\/"
            }
        ],
        "properties": [

        ],
        "constants": [
            {
                "name": "NONE",
                "value": 0,
                "doc": null
            },
            {
                "name": "ELEMENT",
                "value": 1,
                "doc": null
            },
            {
                "name": "ATTRIBUTE",
                "value": 2,
                "doc": null
            },
            {
                "name": "TEXT",
                "value": 3,
                "doc": null
            },
            {
                "name": "CDATA",
                "value": 4,
                "doc": null
            },
            {
                "name": "ENTITY_REF",
                "value": 5,
                "doc": null
            },
            {
                "name": "ENTITY",
                "value": 6,
                "doc": null
            },
            {
                "name": "PI",
                "value": 7,
                "doc": null
            },
            {
                "name": "COMMENT",
                "value": 8,
                "doc": null
            },
            {
                "name": "DOC",
                "value": 9,
                "doc": null
            },
            {
                "name": "DOC_TYPE",
                "value": 10,
                "doc": null
            },
            {
                "name": "DOC_FRAGMENT",
                "value": 11,
                "doc": null
            },
            {
                "name": "NOTATION",
                "value": 12,
                "doc": null
            },
            {
                "name": "WHITESPACE",
                "value": 13,
                "doc": null
            },
            {
                "name": "SIGNIFICANT_WHITESPACE",
                "value": 14,
                "doc": null
            },
            {
                "name": "END_ELEMENT",
                "value": 15,
                "doc": null
            },
            {
                "name": "END_ENTITY",
                "value": 16,
                "doc": null
            },
            {
                "name": "XML_DECLARATION",
                "value": 17,
                "doc": null
            },
            {
                "name": "LOADDTD",
                "value": 1,
                "doc": null
            },
            {
                "name": "DEFAULTATTRS",
                "value": 2,
                "doc": null
            },
            {
                "name": "VALIDATE",
                "value": 3,
                "doc": null
            },
            {
                "name": "SUBST_ENTITIES",
                "value": 4,
                "doc": null
            }
        ]
    }
]
